<?xml version="1.0" encoding="UTF-8"?>
<!--
Copyright (C) 2015 - Today: GRAP (http://www.grap.coop)
@author Sylvain LE GAL (https://twitter.com/legalsylvain)
License AGPL-3.0 or later (http://www.gnu.org/licenses/agpl.html).
-->

<openerp><data>

    <!-- Sale Pricelists -->
    <record id="sale_pricelist" model="product.pricelist">
        <field name="name">Sale Pricelist Intercompany Trade</field>
        <field name="type">sale</field>
        <field name="company_id" ref="intercompany_trade_base.supplier_company"/>
    </record>

    <record id="sale_pricelist_version" model="product.pricelist.version">
        <field name="name">Sale Pricelist Intercompany Trade</field>
        <field name="pricelist_id" ref="sale_pricelist"/>
    </record>

    <record id="sale_pricelist_item" model="product.pricelist.item">
        <field name="name">Sale Pricelist Intercompany Trade</field>
        <field name="price_version_id" ref="sale_pricelist_version"/>
        <field name="base" ref="product.list_price"/>
    </record>

    <record id="pricelist_discount" model="product.pricelist">
        <field name="name">Intercompany Trade - Sale Pricelist (Discount)</field>
        <field name="type">sale</field>
    </record>

    <record id="pricelist_version_discount" model="product.pricelist.version">
        <field name="name">Intercompany Trade - Sale Pricelist Version (Discount)</field>
        <field name="pricelist_id" ref="pricelist_discount"/>
    </record>

    <record id="pricelist_item_discount" model="product.pricelist.item">
        <field name="name">Intercompany Trade - Sale Pricelist Item (Discount)</field>
        <field name="price_version_id" ref="pricelist_version_discount"/>
        <field name="base" eval="1" />
        <field name="price_surcharge">-0.10</field>
    </record>


    <!-- Sale Pricelists -->
    <record id="purchase_pricelist" model="product.pricelist">
        <field name="name">Purchase Pricelist Intercompany Trade</field>
        <field name="type">purchase</field>
        <field name="company_id" ref="intercompany_trade_base.customer_company"/>
    </record>

    <record id="purchase_pricelist_version" model="product.pricelist.version">
        <field name="name">Purchase Pricelist Intercompany Trade</field>
        <field name="pricelist_id" ref="purchase_pricelist"/>
    </record>

    <record id="purchase_pricelist_item" model="product.pricelist.item">
        <field name="name">Purchase Pricelist Intercompany Trade</field>
        <field name="price_version_id" ref="purchase_pricelist_version"/>
        <field name="base" ref="product.list_price"/>
    </record>

</data></openerp>
